upc_checker_pyo3-0.1.3.dist-info/METADATA
upc_checker_pyo3-0.1.3.dist-info/WHEEL
upc_checker.cpython-36m-x86_64-linux-gnu.so
upc_checker_pyo3-0.1.3.dist-info/RECORD
