Metadata-Version: 2.1
Name: upc-checker-pyo3
Version: 0.1.3
Summary: README.md
Author: scOwez <owez@scalist.net>
Author-Email: scOwez <owez@scalist.net>
License: MIT
